<xml xmlns:o="urn:schemas-microsoft-com:office:office">
 <o:MainFile HRef="../index.htm"/>
 <o:File HRef="index_31692_image001.png" PublicationID="index_31692"/>
 <o:File HRef="index_31692_image002.png" PublicationID="index_31692"/>
 <o:File HRef="index_31692_image003.png" PublicationID="index_31692"/>
 <o:File HRef="index_31692_image004.png" PublicationID="index_31692"/>
 <o:File HRef="index_31692_image005.png" PublicationID="index_31692"/>
 <o:File HRef="index_31692_image006.png" PublicationID="index_31692"/>
 <o:File HRef="index_31692_image007.png" PublicationID="index_31692"/>
 <o:File HRef="index_31692_image008.png" PublicationID="index_31692"/>
 <o:File HRef="index_31692_image009.png" PublicationID="index_31692"/>
 <o:File HRef="index_31692_image010.png" PublicationID="index_31692"/>
 <o:File HRef="index_31692_image011.png" PublicationID="index_31692"/>
 <o:File HRef="index_31692_image012.png" PublicationID="index_31692"/>
 <o:File HRef="index_31692_image013.png" PublicationID="index_31692"/>
 <o:File HRef="index_31692_image014.png" PublicationID="index_31692"/>
 <o:File HRef="index_31692_image015.png" PublicationID="index_31692"/>
 <o:File HRef="index_31692_image016.png" PublicationID="index_31692"/>
 <o:File HRef="index_31692_image017.png" PublicationID="index_31692"/>
 <o:File HRef="index_31692_image018.png" PublicationID="index_31692"/>
 <o:File HRef="index_31692_image019.png" PublicationID="index_31692"/>
 <o:File HRef="index_31692_image020.png" PublicationID="index_31692"/>
 <o:File HRef="index_31692_image021.png" PublicationID="index_31692"/>
 <o:File HRef="index_31692_image022.png" PublicationID="index_31692"/>
 <o:File HRef="index_31692_image023.png" PublicationID="index_31692"/>
 <o:File HRef="index_31692_image024.png" PublicationID="index_31692"/>
 <o:File HRef="index_31692_image025.png" PublicationID="index_31692"/>
 <o:File HRef="index_31692_image026.png" PublicationID="index_31692"/>
 <o:File HRef="index_31692_image027.png" PublicationID="index_31692"/>
 <o:File HRef="index_31692_image028.png" PublicationID="index_31692"/>
 <o:File HRef="index_31692_image029.png" PublicationID="index_31692"/>
 <o:File HRef="index_31692_image030.png" PublicationID="index_31692"/>
 <o:File HRef="index_31692_image031.png" PublicationID="index_31692"/>
 <o:File HRef="index_31692_image032.png" PublicationID="index_31692"/>
 <o:File HRef="index_31692_image033.png" PublicationID="index_31692"/>
 <o:File HRef="index_31692_image034.png" PublicationID="index_31692"/>
 <o:File HRef="index_31692_image035.png" PublicationID="index_31692"/>
 <o:File HRef="index_31692_image036.png" PublicationID="index_31692"/>
 <o:File HRef="index_31692_image037.png" PublicationID="index_31692"/>
 <o:File HRef="index_31692_image038.png" PublicationID="index_31692"/>
 <o:File HRef="index_31692_image039.png" PublicationID="index_31692"/>
 <o:File HRef="index_31692_image040.png" PublicationID="index_31692"/>
 <o:File HRef="index_31692_image041.png" PublicationID="index_31692"/>
 <o:File HRef="index_31692_image042.png" PublicationID="index_31692"/>
 <o:File HRef="index_31692_image043.png" PublicationID="index_31692"/>
 <o:File HRef="index_31692_image044.png" PublicationID="index_31692"/>
 <o:File HRef="filelist.xml"/>
</xml>